wavestate/utilities/__init__.py
wavestate/utilities/_version.py
wavestate/utilities/args.py
wavestate/utilities/np.py
wavestate/utilities/pprint.py
wavestate/utilities/strings.py
wavestate/utilities/arguments/__init__.py
wavestate/utilities/arguments/aid.py
wavestate/utilities/arguments/base.py
wavestate/utilities/arguments/logging.py
wavestate/utilities/arguments/pyargparse.py
wavestate/utilities/file_io/__init__.py
wavestate/utilities/file_io/any_io.py
wavestate/utilities/file_io/csv_io.py
wavestate/utilities/file_io/hdf5_io.py
wavestate/utilities/file_io/ini_io.py
wavestate/utilities/file_io/json_io.py
wavestate/utilities/file_io/matlab_io.py
wavestate/utilities/file_io/pickle_io.py
wavestate/utilities/file_io/types.py
wavestate/utilities/file_io/utilities.py
wavestate/utilities/file_io/yaml_io.py
wavestate/utilities/ipynb/__init__.py
wavestate/utilities/ipynb/displays.py
wavestate/utilities/ipynb/sympy.py
wavestate/utilities/mpl/__init__.py
wavestate/utilities/mpl/autoniceplot.py
wavestate/utilities/mpl/colors.py
wavestate/utilities/mpl/logticks.py
wavestate/utilities/mpl/stacked_plots.py
wavestate/utilities/mpl/utils.py
wavestate/utilities/priority_queue/__init__.py
wavestate.utilities-0.9.1.dist-info/METADATA
wavestate.utilities-0.9.1.dist-info/NOTICE
wavestate.utilities-0.9.1.dist-info/WHEEL
wavestate.utilities-0.9.1.dist-info/top_level.txt
wavestate.utilities-0.9.1.dist-info/RECORD
